README.md
setup.py
dev_pacakge.egg-info/PKG-INFO
dev_pacakge.egg-info/SOURCES.txt
dev_pacakge.egg-info/dependency_links.txt
dev_pacakge.egg-info/entry_points.txt
dev_pacakge.egg-info/namespace_packages.txt
dev_pacakge.egg-info/requires.txt
dev_pacakge.egg-info/top_level.txt
orangecontrib/__init__.py
orangecontrib/dev/__init__.py
orangecontrib/dev/widgets/Chatbot.py
orangecontrib/dev/widgets/DocumentEater.py
orangecontrib/dev/widgets/EmbeddingsCreation.py
orangecontrib/dev/widgets/LanguageModel.py
orangecontrib/dev/widgets/TextPreprocessing.py
orangecontrib/dev/widgets/__init__.py
orangecontrib/dev/widgets/goto.py
orangecontrib/dev/widgets/icons/Chatbot.svg
orangecontrib/dev/widgets/icons/DocumentEater.svg
orangecontrib/dev/widgets/icons/Embeddings.svg
orangecontrib/dev/widgets/icons/LanguageModel.svg
orangecontrib/dev/widgets/icons/TextPreprocessing.svg