Metadata-Version: 1.0
Name: dev-pacakge
Version: 0.1
Summary: A package to use our built-in widgets
Home-page: UNKNOWN
Author: HKH
Author-email: UNKNOWN
License: UNKNOWN
Keywords: orange3 add-on
Platform: UNKNOWN
